adbactivityautolite/README.MD
adbactivityautolite/__init__.py
adbactivityautolite/requirements.txt
adbactivityautolite/thirdparty.json
adbactivityautolite-0.10.dist-info/LICENSE.rst
adbactivityautolite-0.10.dist-info/METADATA
adbactivityautolite-0.10.dist-info/WHEEL
adbactivityautolite-0.10.dist-info/top_level.txt
adbactivityautolite-0.10.dist-info/RECORD
