Metadata-Version: 2.1
Name: adbactivityautolite
Version: 0.10
Summary: Uses -dumpsys activity top- instead of -uiautomator- to automate Android
Home-page: https://github.com/hansalemaos/adbactivityautolite
Author: Johannes Fischer
Author-email: aulasparticularesdealemaosp@gmail.com
License: MIT
Keywords: adb,DataFrame,pandas,android,automation
Classifier: Development Status :: 4 - Beta
Classifier: Programming Language :: Python :: 3 :: Only
Classifier: Programming Language :: Python :: 3.10
Classifier: Topic :: Software Development :: Libraries :: Python Modules
Classifier: Topic :: Utilities
License-File: LICENSE.rst
Requires-Dist: a-pandas-ex-apply-ignore-exceptions
Requires-Dist: a-pandas-ex-less-memory-more-speed
Requires-Dist: numpy
Requires-Dist: pandas
Requires-Dist: regex
Requires-Dist: usefuladb
